[
  {"model": "services.servicecategory", "pk":  1, "fields": {"slug": "cleaning",          "icon": "cleaning_services", "order":  0}},
  {"model": "services.servicecategory", "pk":  2, "fields": {"slug": "maintenance",       "icon": "handyman",           "order":  1}},
  {"model": "services.servicecategory", "pk":  3, "fields": {"slug": "moving",            "icon": "local_shipping",     "order":  2}},
  {"model": "services.servicecategory", "pk":  4, "fields": {"slug": "beauty",            "icon": "spa",                "order":  3}},
  {"model": "services.servicecategory", "pk":  5, "fields": {"slug": "tutoring",          "icon": "school",             "order":  4}},
  {"model": "services.servicecategory", "pk":  6, "fields": {"slug": "catering",          "icon": "restaurant",         "order":  5}},
  {"model": "services.servicecategory", "pk":  7, "fields": {"slug": "photography",       "icon": "photo_camera",       "order":  6}},
  {"model": "services.servicecategory", "pk":  8, "fields": {"slug": "design",            "icon": "design_services",    "order":  7}},
  {"model": "services.servicecategory", "pk":  9, "fields": {"slug": "it_support",        "icon": "computer",           "order":  8}},
  {"model": "services.servicecategory", "pk": 10, "fields": {"slug": "legal",             "icon": "gavel",              "order":  9}},
  {"model": "services.servicecategory", "pk": 11, "fields": {"slug": "medical",           "icon": "local_hospital",     "order": 10}},
  {"model": "services.servicecategory", "pk": 12, "fields": {"slug": "events_management", "icon": "event",              "order": 11}},
  {"model": "services.servicecategory", "pk": 13, "fields": {"slug": "other",             "icon": "category",           "order": 12}},

  {"model": "services.servicecategorytranslation", "pk":  1, "fields": {"master":  1, "language_code": "ar", "name": "تنظيف"}},
  {"model": "services.servicecategorytranslation", "pk":  2, "fields": {"master":  1, "language_code": "en", "name": "Cleaning"}},
  {"model": "services.servicecategorytranslation", "pk":  3, "fields": {"master":  2, "language_code": "ar", "name": "صيانة"}},
  {"model": "services.servicecategorytranslation", "pk":  4, "fields": {"master":  2, "language_code": "en", "name": "Maintenance"}},
  {"model": "services.servicecategorytranslation", "pk":  5, "fields": {"master":  3, "language_code": "ar", "name": "نقل عفش"}},
  {"model": "services.servicecategorytranslation", "pk":  6, "fields": {"master":  3, "language_code": "en", "name": "Moving"}},
  {"model": "services.servicecategorytranslation", "pk":  7, "fields": {"master":  4, "language_code": "ar", "name": "تجميل"}},
  {"model": "services.servicecategorytranslation", "pk":  8, "fields": {"master":  4, "language_code": "en", "name": "Beauty"}},
  {"model": "services.servicecategorytranslation", "pk":  9, "fields": {"master":  5, "language_code": "ar", "name": "تدريس"}},
  {"model": "services.servicecategorytranslation", "pk": 10, "fields": {"master":  5, "language_code": "en", "name": "Tutoring"}},
  {"model": "services.servicecategorytranslation", "pk": 11, "fields": {"master":  6, "language_code": "ar", "name": "تموين"}},
  {"model": "services.servicecategorytranslation", "pk": 12, "fields": {"master":  6, "language_code": "en", "name": "Catering"}},
  {"model": "services.servicecategorytranslation", "pk": 13, "fields": {"master":  7, "language_code": "ar", "name": "تصوير"}},
  {"model": "services.servicecategorytranslation", "pk": 14, "fields": {"master":  7, "language_code": "en", "name": "Photography"}},
  {"model": "services.servicecategorytranslation", "pk": 15, "fields": {"master":  8, "language_code": "ar", "name": "تصميم"}},
  {"model": "services.servicecategorytranslation", "pk": 16, "fields": {"master":  8, "language_code": "en", "name": "Design"}},
  {"model": "services.servicecategorytranslation", "pk": 17, "fields": {"master":  9, "language_code": "ar", "name": "دعم تقني"}},
  {"model": "services.servicecategorytranslation", "pk": 18, "fields": {"master":  9, "language_code": "en", "name": "IT Support"}},
  {"model": "services.servicecategorytranslation", "pk": 19, "fields": {"master": 10, "language_code": "ar", "name": "خدمات قانونية"}},
  {"model": "services.servicecategorytranslation", "pk": 20, "fields": {"master": 10, "language_code": "en", "name": "Legal"}},
  {"model": "services.servicecategorytranslation", "pk": 21, "fields": {"master": 11, "language_code": "ar", "name": "طبية"}},
  {"model": "services.servicecategorytranslation", "pk": 22, "fields": {"master": 11, "language_code": "en", "name": "Medical"}},
  {"model": "services.servicecategorytranslation", "pk": 23, "fields": {"master": 12, "language_code": "ar", "name": "تنظيم فعاليات"}},
  {"model": "services.servicecategorytranslation", "pk": 24, "fields": {"master": 12, "language_code": "en", "name": "Events Management"}},
  {"model": "services.servicecategorytranslation", "pk": 25, "fields": {"master": 13, "language_code": "ar", "name": "أخرى"}},
  {"model": "services.servicecategorytranslation", "pk": 26, "fields": {"master": 13, "language_code": "en", "name": "Other"}}
]
